nox_pdm-0.0.3.dist-info/METADATA
nox_pdm-0.0.3.dist-info/WHEEL
nox_pdm-0.0.3.dist-info/entry_points.txt
nox_pdm-0.0.3.dist-info/licenses/LICENSE
nox_pdm/__init__.py
nox_pdm/py.typed
nox_pdm/sessions.py
nox_pdm-0.0.3.dist-info/RECORD
