Metadata-Version: 2.1
Name: nox-pdm
Version: 0.0.3
Summary: Use PDM inside Nox sessions
Author-Email: "Ashwin V. Mohanan" <dev@fluid.quest>
License: Apache-2.0
Classifier: License :: OSI Approved :: BSD License
Classifier: Programming Language :: Python :: 3 :: Only
Classifier: Programming Language :: Python :: 3.9
Classifier: Programming Language :: Python :: 3.10
Classifier: Programming Language :: Python :: 3.11
Classifier: Programming Language :: Python :: 3.12
Classifier: Programming Language :: Python :: 3.13
Classifier: Topic :: Software Development :: Testing
Project-URL: Homepage, https://codeberg.org/ashwinvis/nox-pdm
Project-URL: Bug Tracker, https://codeberg.org/ashwinvis/nox-pdm/issues
Requires-Python: >=3.9
Requires-Dist: nox>=2023.4.22
Provides-Extra: tests
Requires-Dist: pytest>=8.0.0; extra == "tests"
Requires-Dist: urllib3==2.1.0; extra == "tests"
Requires-Dist: pytest-cov>=4.1.0; extra == "tests"
Requires-Dist: pytest-icdiff>=0.8; extra == "tests"
Provides-Extra: types
Requires-Dist: mypy[reports]>=1.8.0; extra == "types"
